ua_parser_rs-0.1.4.dist-info/METADATA
ua_parser_rs-0.1.4.dist-info/WHEEL
ua_parser_rs-0.1.4.dist-info/licenses/LICENSE
ua_parser_rs/__init__.py
ua_parser_rs/__init__.pyi
ua_parser_rs/py.typed
ua_parser_rs/ua_parser_rs.abi3.so
ua_parser_rs-0.1.4.dist-info/RECORD
