Metadata-Version: 2.4
Name: ua-parser-rs
Version: 0.1.4
Classifier: Programming Language :: Rust
Classifier: Programming Language :: Python :: 3.10
Classifier: Programming Language :: Python :: 3.11
Classifier: Programming Language :: Python :: 3.12
Classifier: Programming Language :: Python :: 3.13
Classifier: Programming Language :: Python :: 3.14
Classifier: Programming Language :: Python :: Implementation :: CPython
Classifier: Programming Language :: Python :: Implementation :: PyPy
Classifier: Programming Language :: Python :: Implementation :: GraalPy
Classifier: License :: OSI Approved :: Apache Software License
License-File: LICENSE
Summary: native accelerator for ua-parser
Home-Page: https://github.com/ua-parser/uap-rust/blob/main/ua-parser/
License: Apache 2.0
Requires-Python: >=3.10
Project-URL: Homepage, https://github.com/ua-parser/uap-rust/blob/main/ua-parser/
Project-URL: Source Code, https://github.com/ua-parser/uap-rust/
